odoo/addons/base_user_locale/README.rst
odoo/addons/base_user_locale/__init__.py
odoo/addons/base_user_locale/__manifest__.py
odoo/addons/base_user_locale/controllers/__init__.py
odoo/addons/base_user_locale/controllers/web_client.py
odoo/addons/base_user_locale/i18n/base_user_locale.pot
odoo/addons/base_user_locale/i18n/es.po
odoo/addons/base_user_locale/i18n/it.po
odoo/addons/base_user_locale/models/__init__.py
odoo/addons/base_user_locale/models/calendar_event.py
odoo/addons/base_user_locale/models/res_company.py
odoo/addons/base_user_locale/models/res_config_settings.py
odoo/addons/base_user_locale/models/res_users.py
odoo/addons/base_user_locale/readme/CONTRIBUTORS.rst
odoo/addons/base_user_locale/readme/DESCRIPTION.rst
odoo/addons/base_user_locale/readme/USAGE.rst
odoo/addons/base_user_locale/static/description/icon.png
odoo/addons/base_user_locale/static/description/index.html
odoo/addons/base_user_locale/tests/__init__.py
odoo/addons/base_user_locale/tests/test_base_user_locale.py
odoo/addons/base_user_locale/views/res_config_settings.xml
odoo/addons/base_user_locale/views/res_users.xml
odoo_addon_base_user_locale-16.0.1.1.1.dist-info/METADATA
odoo_addon_base_user_locale-16.0.1.1.1.dist-info/WHEEL
odoo_addon_base_user_locale-16.0.1.1.1.dist-info/top_level.txt
odoo_addon_base_user_locale-16.0.1.1.1.dist-info/RECORD
